{
    "input_dict": {
        "progname": "Ex10",
        "candidate": "(x7 || !x9) && (!x7 || x9)",
        "init_states": "(x7 || !x9) && (!x7 || x9) && (x12 || !x16) && (!x12 || x16)",
        "iterations": 1
    },
    "parameters_dict": {
        "epsilon": 0.05,
        "delta": 0.1,
        "t": 500
    },
    "output_dict": {
        "Sampled output states": [
            55300,
            24581,
            18438,
            45067,
            59403,
            14348,
            51214,
            53260,
            22542,
            12305,
            24593,
            22548,
            61461,
            14361,
            20507,
            63516,
            38939,
            20513,
            32801,
            12322,
            43044,
            18466,
            55329,
            22567,
            61475,
            34867,
            18484,
            38965,
            57397,
            30778,
            6202,
            53309,
            18495,
            6209,
            49217,
            28749,
            51280,
            32850,
            49247,
            4193,
            45157,
            26726,
            24684,
            49261,
            57456,
            30835,
            30837,
            30842,
            6274,
            10370,
            49282,
            59525,
            30850,
            53381,
            18565,
            55435,
            39051,
            57485,
            147,
            18581,
            63640,
            18590,
            159,
            16543,
            61599,
            2210,
            10407,
            57512,
            57511,
            14506,
            63659,
            2220,
            57517,
            2221,
            4270,
            14509,
            55474,
            6324,
            28853,
            10422,
            32952,
            30908,
            35006,
            28867,
            39111,
            43209,
            35017,
            49355,
            43210,
            20685,
            26832,
            210,
            24789,
            37078,
            41177,
            37083,
            61659,
            51420,
            6366,
            24795,
            20704,
            45282,
            45283,
            14564,
            35044,
            18661,
            55527,
            61667,
            43235,
            37098,
            51435,
            55532,
            26857,
            55534,
            8433,
            37106,
            16627,
            49395,
            24817,
            30972,
            112895,
            28927,
            22440,
            16375,
            57857,
            41474,
            59909,
            14854,
            61961,
            64012,
            29196,
            8719,
            10768,
            12818,
            31252,
            23061,
            2580,
            8727,
            55833,
            6682,
            23067,
            29212,
            4633,
            31264,
            546,
            4643,
            45605,
            21033,
            18985,
            57902,
            25136,
            43569,
            25141,
            568,
            62008,
            2617,
            43578,
            14904,
            47678,
            29248,
            31299,
            57925,
            19019,
            39500,
            2637,
            4686,
            53841,
            10835,
            64084,
            39509,
            49750,
            12883,
            62040,
            53857,
            2658,
            6753,
            31338,
            21100,
            19054,
            12911,
            47734,
            45687,
            2684,
            39550,
            47743,
            21128,
            31369,
            62090,
            47753,
            55946,
            17032,
            31378,
            6803,
            49813,
            62101,
            31384,
            17049,
            51870,
            23198,
            62113,
            21155,
            41641,
            53935,
            15023,
            39602,
            45749,
            43701,
            15030,
            6847,
            45760,
            39616,
            25284,
            12998,
            58055,
            47816,
            8905,
            17098,
            25289,
            62155,
            19148,
            10953,
            41681,
            29400,
            31450,
            41690,
            47837,
            15069,
            2781,
            62176,
            49890,
            29413,
            58087,
            41706,
            35563,
            29422,
            35567,
            21230,
            37618,
            4851,
            39668,
            45811,
            17142,
            56052,
            56062,
            21762,
            13572,
            23813,
            56580,
            7430,
            15620,
            27917,
            21773,
            9487,
            5395,
            15642,
            32027,
            42270,
            9503,
            38181,
            29997,
            50480,
            17714,
            50483,
            42293,
            58678,
            9528,
            48442,
            58683,
            40260,
            9545,
            17738,
            64844,
            64845,
            5458,
            42326,
            13656,
            36184,
            7514,
            58716,
            40286,
            52575,
            3429,
            60773,
            42348,
            54638,
            54645,
            9591,
            11641,
            62841,
            25977,
            13692,
            64897,
            19841,
            34179,
            25988,
            44421,
            48518,
            38278,
            62856,
            40328,
            48523,
            52622,
            3473,
            28051,
            38291,
            36245,
            48533,
            17816,
            64929,
            50596,
            5544,
            52649,
            54703,
            1458,
            54711,
            32185,
            54714,
            42426,
            7619,
            21955,
            19917,
            26061,
            17880,
            30170,
            3547,
            30172,
            42461,
            38364,
            3551,
            38372,
            9702,
            65003,
            42476,
            15852,
            7662,
            19950,
            38382,
            36337,
            19953,
            56816,
            42484,
            42486,
            56823,
            50685,
            55291,
            59137,
            7937,
            44803,
            24324,
            16130,
            9986,
            63239,
            50957,
            16142,
            50959,
            24336,
            14097,
            32532,
            24350,
            57119,
            65316,
            28453,
            55081,
            20276,
            44853,
            63285,
            7993,
            36666,
            46907,
            20281,
            48953,
            46911,
            59200,
            40771,
            10052,
            51012,
            65350,
            3907,
            8009,
            28490,
            40778,
            5961,
            3919,
            18256,
            5968,
            14161,
            34639,
            16210,
            20303,
            38742,
            53079,
            46937,
            22363,
            38748,
            14173,
            10077,
            46942,
            65375,
            59233,
            44898,
            3940,
            3941,
            8040,
            40809,
            46953,
            8042,
            65387,
            28526,
            51058,
            26482,
            49012,
            42869,
            20344,
            57212,
            53118,
            40831,
            49025,
            30597,
            26504,
            1929,
            26506,
            30604,
            10126,
            53134,
            44944,
            30610,
            55189,
            44949,
            53141,
            49048,
            26523,
            47007,
            20385,
            44961,
            30627,
            28580,
            28582,
            20390,
            10150,
            65446,
            47018,
            55211,
            47017,
            18349,
            57262,
            28590,
            8112,
            22449,
            55216,
            57267,
            26548,
            61361,
            8109,
            49079,
            22456,
            36794,
            14269,
            4029,
            26560,
            47043,
            16323,
            44996,
            30659,
            36807,
            26574,
            32719,
            47056,
            65488,
            4053,
            8154,
            38876,
            26589,
            49118,
            30684,
            40931,
            57317,
            38886,
            20453,
            45032,
            55272,
            65514,
            28653,
            18414,
            6130,
            22515,
            36852,
            10231,
            63482,
            20475,
            100351
        ],
        "Validifier_value": 0.478,
        "counterexamples": {
            "41474": 0.0020408163265306124,
            "14854": 0.0020408163265306124,
            "18438": 0.0020408163265306124,
            "45067": 0.0020408163265306124,
            "59403": 0.0020408163265306124,
            "22542": 0.0020408163265306124,
            "8719": 0.0020408163265306124,
            "12818": 0.0020408163265306124,
            "8727": 0.0020408163265306124,
            "6682": 0.0020408163265306124,
            "20507": 0.0020408163265306124,
            "23067": 0.0020408163265306124,
            "38939": 0.0020408163265306124,
            "31264": 0.0020408163265306124,
            "20513": 0.0020408163265306124,
            "32801": 0.0020408163265306124,
            "55329": 0.0020408163265306124,
            "43044": 0.0020408163265306124,
            "45605": 0.0020408163265306124,
            "21033": 0.0020408163265306124,
            "18985": 0.0020408163265306124,
            "25136": 0.0020408163265306124,
            "43569": 0.0020408163265306124,
            "18484": 0.0020408163265306124,
            "25141": 0.0020408163265306124,
            "38965": 0.0020408163265306124,
            "57397": 0.0020408163265306124,
            "568": 0.0020408163265306124,
            "62008": 0.0020408163265306124,
            "2617": 0.0020408163265306124,
            "14904": 0.0020408163265306124,
            "53309": 0.0020408163265306124,
            "31299": 0.0020408163265306124,
            "19019": 0.0020408163265306124,
            "4686": 0.0020408163265306124,
            "32850": 0.0020408163265306124,
            "10835": 0.0020408163265306124,
            "12883": 0.0020408163265306124,
            "49750": 0.0020408163265306124,
            "49247": 0.0020408163265306124,
            "53857": 0.0020408163265306124,
            "4193": 0.0020408163265306124,
            "6753": 0.0020408163265306124,
            "45157": 0.0020408163265306124,
            "24684": 0.0020408163265306124,
            "21100": 0.0020408163265306124,
            "49261": 0.0020408163265306124,
            "57456": 0.0020408163265306124,
            "30837": 0.0020408163265306124,
            "2684": 0.0020408163265306124,
            "6274": 0.0020408163265306124,
            "10370": 0.0020408163265306124,
            "49282": 0.0020408163265306124,
            "30850": 0.0020408163265306124,
            "62090": 0.0020408163265306124,
            "55435": 0.0020408163265306124,
            "55946": 0.0020408163265306124,
            "39051": 0.0020408163265306124,
            "31378": 0.0020408163265306124,
            "6803": 0.0020408163265306124,
            "147": 0.0020408163265306124,
            "18590": 0.0020408163265306124,
            "51870": 0.0020408163265306124,
            "23198": 0.0020408163265306124,
            "62113": 0.0020408163265306124,
            "159": 0.0020408163265306124,
            "16543": 0.0020408163265306124,
            "61599": 0.0020408163265306124,
            "57512": 0.0020408163265306124,
            "41641": 0.0020408163265306124,
            "2220": 0.0020408163265306124,
            "57517": 0.0020408163265306124,
            "2221": 0.0020408163265306124,
            "14509": 0.0020408163265306124,
            "6324": 0.0020408163265306124,
            "28853": 0.0020408163265306124,
            "45749": 0.0020408163265306124,
            "43701": 0.0020408163265306124,
            "32952": 0.0020408163265306124,
            "30908": 0.0020408163265306124,
            "28867": 0.0020408163265306124,
            "12998": 0.0020408163265306124,
            "39111": 0.0020408163265306124,
            "58055": 0.0020408163265306124,
            "17098": 0.0020408163265306124,
            "62155": 0.0020408163265306124,
            "49355": 0.0020408163265306124,
            "43210": 0.0020408163265306124,
            "210": 0.0020408163265306124,
            "37078": 0.0020408163265306124,
            "31450": 0.0020408163265306124,
            "61659": 0.0020408163265306124,
            "41690": 0.0020408163265306124,
            "37083": 0.0020408163265306124,
            "6366": 0.0020408163265306124,
            "24795": 0.0020408163265306124,
            "20704": 0.0020408163265306124,
            "62176": 0.0020408163265306124,
            "35044": 0.0020408163265306124,
            "18661": 0.0020408163265306124,
            "14564": 0.0020408163265306124,
            "29413": 0.0020408163265306124,
            "26857": 0.0020408163265306124,
            "55532": 0.0020408163265306124,
            "8433": 0.0020408163265306124,
            "24817": 0.0020408163265306124,
            "39668": 0.0020408163265306124,
            "56052": 0.0020408163265306124,
            "30972": 0.0020408163265306124,
            "21762": 0.0020408163265306124,
            "44803": 0.0020408163265306124,
            "16130": 0.0020408163265306124,
            "9986": 0.0020408163265306124,
            "7430": 0.0020408163265306124,
            "63239": 0.0020408163265306124,
            "16142": 0.0020408163265306124,
            "50959": 0.0020408163265306124,
            "9487": 0.0020408163265306124,
            "5395": 0.0020408163265306124,
            "15642": 0.0020408163265306124,
            "32027": 0.0020408163265306124,
            "24350": 0.0020408163265306124,
            "57119": 0.0020408163265306124,
            "9503": 0.0020408163265306124,
            "42270": 0.0020408163265306124,
            "65316": 0.0020408163265306124,
            "28453": 0.0020408163265306124,
            "38181": 0.0020408163265306124,
            "55081": 0.0020408163265306124,
            "29997": 0.0020408163265306124,
            "50480": 0.0020408163265306124,
            "20276": 0.0020408163265306124,
            "42293": 0.0020408163265306124,
            "44853": 0.0020408163265306124,
            "63285": 0.0020408163265306124,
            "9528": 0.0020408163265306124,
            "7993": 0.0020408163265306124,
            "20281": 0.0020408163265306124,
            "48953": 0.0020408163265306124,
            "40771": 0.0020408163265306124,
            "3907": 0.0020408163265306124,
            "65350": 0.0020408163265306124,
            "17738": 0.0020408163265306124,
            "28490": 0.0020408163265306124,
            "40778": 0.0020408163265306124,
            "3919": 0.0020408163265306124,
            "34639": 0.0020408163265306124,
            "20303": 0.0020408163265306124,
            "16210": 0.0020408163265306124,
            "5458": 0.0020408163265306124,
            "38742": 0.0020408163265306124,
            "53079": 0.0020408163265306124,
            "42326": 0.0020408163265306124,
            "7514": 0.0020408163265306124,
            "22363": 0.0020408163265306124,
            "40286": 0.0020408163265306124,
            "46942": 0.0020408163265306124,
            "65375": 0.0020408163265306124,
            "59233": 0.0020408163265306124,
            "52575": 0.0020408163265306124,
            "3940": 0.0020408163265306124,
            "3941": 0.0020408163265306124,
            "3429": 0.0020408163265306124,
            "60773": 0.0020408163265306124,
            "8040": 0.0020408163265306124,
            "40809": 0.0020408163265306124,
            "46953": 0.0020408163265306124,
            "42348": 0.0020408163265306124,
            "49012": 0.0020408163265306124,
            "54645": 0.0020408163265306124,
            "42869": 0.0020408163265306124,
            "20344": 0.0020408163265306124,
            "11641": 0.0020408163265306124,
            "62841": 0.0020408163265306124,
            "25977": 0.0020408163265306124,
            "13692": 0.0020408163265306124,
            "57212": 0.0020408163265306124,
            "34179": 0.0020408163265306124,
            "48518": 0.0020408163265306124,
            "38278": 0.0020408163265306124,
            "26506": 0.0020408163265306124,
            "48523": 0.0020408163265306124,
            "10126": 0.0020408163265306124,
            "53134": 0.0020408163265306124,
            "52622": 0.0020408163265306124,
            "30610": 0.0020408163265306124,
            "28051": 0.0020408163265306124,
            "38291": 0.0020408163265306124,
            "26523": 0.0020408163265306124,
            "47007": 0.0020408163265306124,
            "64929": 0.0020408163265306124,
            "20385": 0.0020408163265306124,
            "44961": 0.0020408163265306124,
            "28580": 0.0020408163265306124,
            "50596": 0.0020408163265306124,
            "22440": 0.0020408163265306124,
            "47017": 0.0020408163265306124,
            "52649": 0.0020408163265306124,
            "5544": 0.0020408163265306124,
            "18349": 0.0020408163265306124,
            "8109": 0.0020408163265306124,
            "8112": 0.0020408163265306124,
            "22449": 0.0020408163265306124,
            "55216": 0.0020408163265306124,
            "61361": 0.0020408163265306124,
            "26548": 0.0020408163265306124,
            "22456": 0.0020408163265306124,
            "32185": 0.0020408163265306124,
            "14269": 0.0020408163265306124,
            "4029": 0.0020408163265306124,
            "47043": 0.0020408163265306124,
            "7619": 0.0020408163265306124,
            "16323": 0.0020408163265306124,
            "21955": 0.0020408163265306124,
            "36807": 0.0020408163265306124,
            "30659": 0.0020408163265306124,
            "26574": 0.0020408163265306124,
            "32719": 0.0020408163265306124,
            "8154": 0.0020408163265306124,
            "3547": 0.0020408163265306124,
            "30170": 0.0020408163265306124,
            "49118": 0.0020408163265306124,
            "3551": 0.0020408163265306124,
            "38372": 0.0020408163265306124,
            "57317": 0.0020408163265306124,
            "20453": 0.0020408163265306124,
            "45032": 0.0020408163265306124,
            "55272": 0.0020408163265306124,
            "42476": 0.0020408163265306124,
            "28653": 0.0020408163265306124,
            "15852": 0.0020408163265306124,
            "56816": 0.0020408163265306124,
            "36337": 0.0020408163265306124,
            "19953": 0.0020408163265306124,
            "36852": 0.0020408163265306124,
            "42484": 0.0020408163265306124,
            "50685": 0.0020408163265306124
        }
    }
}